pipeline/__init__.py
pipeline/cli.py
pipeline/cli_args.py
pipeline/config.py
pipeline/decoders.py
pipeline/main.py
pipeline/mqtt.py
pipeline/producers.py
pipeline/settings.py
pipeline/types.py
pipeline/clients/__init__.py
pipeline/clients/base.py
pipeline/clients/kafka.py
pipeline/clients/mock.py
pipeline/clients/mqtt.py
pipeline/producers/__init__.py
pipeline/producers/base.py
pipeline/producers/kafka.py
pipeline/producers/mock.py
pipeline/producers/timescale.py
pipeline/tests/__init__.py
pipeline/tests/clients_mock_tests.py
pipeline/tests/producers_timescale_tests.py
trell_data_pipeline-0.4.11.dist-info/METADATA
trell_data_pipeline-0.4.11.dist-info/WHEEL
trell_data_pipeline-0.4.11.dist-info/top_level.txt
trell_data_pipeline-0.4.11.dist-info/zip-safe
trell_data_pipeline-0.4.11.dist-info/RECORD
