Metadata-Version: 2.1
Name: trell-data-pipeline
Version: 0.4.11
Summary: Pipes various ingress streams to another egress stream. I.e. MQTT -> Kafka
Home-page: https://github.com/frisellcpl/trell-data-pipeline
Author: Johan Frisell
Author-email: johan@trell.se
License: UNKNOWN
Platform: UNKNOWN
Classifier: Intended Audience :: Developers
Classifier: Topic :: Utilities
Classifier: License :: Public Domain
Classifier: Natural Language :: English
Classifier: Operating System :: OS Independent
Classifier: Programming Language :: Python :: 3.6
Classifier: Programming Language :: Python :: 3.7
Classifier: Programming Language :: Python :: 3.8
Requires-Dist: aiokafka (==0.5.2)
Requires-Dist: asyncpg (==0.20.1)
Requires-Dist: PyYAML (==5.3)
Requires-Dist: gmqtt (==0.5.5)
Requires-Dist: jsonschema (==3.2.0)
Provides-Extra: dev
Requires-Dist: pytest (==2.9.2) ; extra == 'dev'
